README.md
setup.cfg
setup.py
sf_virtual_data/__init__.py
sf_virtual_data/__main__.py
sf_virtual_data/models.py
sf_virtual_data/utils.py
sf_virtual_data/virtual_tags_runner.py
sf_virtual_data.egg-info/PKG-INFO
sf_virtual_data.egg-info/SOURCES.txt
sf_virtual_data.egg-info/dependency_links.txt
sf_virtual_data.egg-info/requires.txt
sf_virtual_data.egg-info/top_level.txt
sf_virtual_data/api/__init__.py
sf_virtual_data/api/vt_pb2.py
sf_virtual_data/api/vt_pb2_grpc.py