Metadata-Version: 1.2
Name: sf-virtual-data
Version: 0.1.0
Summary: SolarFocus library for using virtual data (tables/sfv/trends).
Home-page: https://github.com/brightsource-il/solar-focus-nextgen
Author: BrightSource Industries Israel
Author-email: ModelFresco@brightsourceenergy.com
License: MIT
Project-URL: Tracker, https://redmine.bseinc.com/redmine/projects/solar-focus/issues
Platform: UNKNOWN
Classifier: Programming Language :: Python :: 3
Classifier: License :: OSI Approved :: MIT License
Classifier: Operating System :: OS Independent
Requires-Python: >=3.8
